simple_sqlite3_orm/__init__.py
simple_sqlite3_orm/_sqlite_spec.py
simple_sqlite3_orm/_table_spec.py
simple_sqlite3_orm/_types.py
simple_sqlite3_orm/_typing.py
simple_sqlite3_orm/_utils.py
simple_sqlite3_orm/_version.py
simple_sqlite3_orm/py.typed
simple_sqlite3_orm/utils.py
simple_sqlite3_orm/_orm/__init__.py
simple_sqlite3_orm/_orm/_base.py
simple_sqlite3_orm/_orm/_pool.py
simple_sqlite3_orm/_orm/_utils.py
simple_sqlite3_orm-0.13.0.dist-info/METADATA
simple_sqlite3_orm-0.13.0.dist-info/WHEEL
simple_sqlite3_orm-0.13.0.dist-info/licenses/LICENSE
simple_sqlite3_orm-0.13.0.dist-info/RECORD
