Metadata-Version: 2.4
Name: simple-sqlite3-orm
Version: 0.13.0
Summary: A simple yet powerful SQLite3 ORM, powered by pydantic.
Project-URL: Source, https://github.com/pga2rn/simple-sqlite3-orm
Project-URL: Tracker, https://github.com/pga2rn/simple-sqlite3-orm/issues
Author-email: pga2rn <aaronpigybd@gmail.com>
License-Expression: Apache-2.0
License-File: LICENSE
Classifier: License :: OSI Approved :: Apache Software License
Classifier: Operating System :: OS Independent
Classifier: Programming Language :: Python :: 3 :: Only
Classifier: Programming Language :: Python :: 3.8
Classifier: Programming Language :: Python :: 3.9
Classifier: Programming Language :: Python :: 3.10
Classifier: Programming Language :: Python :: 3.11
Classifier: Programming Language :: Python :: 3.12
Classifier: Programming Language :: Python :: 3.13
Requires-Python: >=3.8
Requires-Dist: pydantic<3,>=2.6
Requires-Dist: typing-extensions>=4
